ass_renderer/__init__.py
ass_renderer/libass.py
ass_renderer/renderer.py
ass_renderer/tests/__init__.py
ass_renderer/tests/test_renderer.py
ass_renderer-0.5.dist-info/licenses/LICENSE.md
ass_renderer-0.5.dist-info/METADATA
ass_renderer-0.5.dist-info/WHEEL
ass_renderer-0.5.dist-info/top_level.txt
ass_renderer-0.5.dist-info/RECORD
