Metadata-Version: 2.4
Name: ass_renderer
Version: 0.5
Summary: Render ASS subtitles as numpy bitmaps.
Author-email: Marcin Kurczewski <dash@wind.garden>
License-Expression: GPL-3.0-or-later
Classifier: Development Status :: 4 - Beta
Classifier: Intended Audience :: Developers
Classifier: Natural Language :: English
Classifier: Operating System :: OS Independent
Classifier: Programming Language :: Python :: 3.9
Classifier: Topic :: Text Processing
Classifier: Topic :: Multimedia :: Graphics
Classifier: Topic :: Software Development :: Libraries :: Python Modules
Requires-Python: >=3.9
License-File: LICENSE.md
Requires-Dist: numpy>=1.21.4
Requires-Dist: ass-parser>=1.0
Requires-Dist: Pillow>=8.4.0
Dynamic: license-file
